Workbook
Name loanlist: 'Loan Out'!$A$2:$A$250
Name paymentlist: Payments!$A$2:$A$250
Name Clientlist: 'Client list'!$A$2:$A$250
Name ClientId: 'Client list'!$A$2:$A$250
Name Clientlist1: 'Client list'!$B$2:$B$250
Name Helpercollist: 'Loan Out'!$K$2:$K$250
Name Flaglist: 'Loan Out'!$L$2:$L$250

Sheet Client list
A1: Client ID | B1: Client Name | C1: Primary contact | D1: Sec contact
A2: =IF(B2<>"","Client"&ROW()-1,"") -> Client1 | B2: Elvis Mbaya | C2: 0712345678
A3: =IF(B3<>"","Client"&ROW()-1,"") -> Client2 | B3: Linda Musita | C3: 0723456789
A4: =IF(B4<>"","Client"&ROW()-1,"") -> Client3 | B4: Pauline Kayaja | C4: 0734567891
A5: =IF(B5<>"","Client"&ROW()-1,"") -> Client4 | B5: Tonny Ngaira | C5: 0745678912
A6: =IF(B6<>"","Client"&ROW()-1,"") -> Client5 | B6: James Nganga | C6: 0756789123 | D6: 0756318769
A7: =IF(B7<>"","Client"&ROW()-1,"") -> Client6 | B7: Edmond Odongo | C7: 0767891234
A8: =IF(B8<>"","Client"&ROW()-1,"") -> Client7 | B8: Aluchio Caren | C8: 0778912345
A9: =IF(B9<>"","Client"&ROW()-1,"") -> Client8 | B9: Felicity | C9: 0789123456
A10: =IF(B10<>"","Client"&ROW()-1,"") -> Client9 | B10: Dennis Nyawira | C10: 0791234567
A11: =IF(B11<>"","Client"&ROW()-1,"")
A12: =IF(B12<>"","Client"&ROW()-1,"")
A13: =IF(B13<>"","Client"&ROW()-1,"")
A14: =IF(B14<>"","Client"&ROW()-1,"")
A15: =IF(B15<>"","Client"&ROW()-1,"")
A16: =IF(B16<>"","Client"&ROW()-1,"")
A17: =IF(B17<>"","Client"&ROW()-1,"")
A18: =IF(B18<>"","Client"&ROW()-1,"")
A19: =IF(B19<>"","Client"&ROW()-1,"")
A20: =IF(B20<>"","Client"&ROW()-1,"")
A21: =IF(B21<>"","Client"&ROW()-1,"")
A22: =IF(B22<>"","Client"&ROW()-1,"")
... A1001: =IF(B1001<>"","Client"&ROW()-1,"")

Sheet Loan Out
A1: Loan ID | B1: Client Name | C1: Client ID | D1: Principal Amount | E1: Transaction cost | F1: Principal + Other costs | G1: Rate | H1: Interest | I1: Expected Amnt | J1: Date | K1: HelperCol | L1: Flagged
A2: =IF(B2<>"","LN"&ROW()-1,"") -> LN1 | B2: Linda Musita | C2: =IF(B2<>"",_xlfn.XLOOKUP(B2,'Client list'!B:B,'Client list'!A:A),"") -> Client2 | D2: 18000 | E2: 105 | F2: =IF(D2<>"",(D2+E2),"") -> 18105 | G2: 0.15 | H2: =IF(D2<>"",(D2*G2),"") -> 2700 | I2: =IF(D2<>"",(D2+H2),"") -> 20700 | J2: 45964 | K2: =IF(D2<>"",(A2&" | "&B2&" | "&D2&" | "&H2&" | "&I2&" | "&J2),"") -> LN1 | Linda Musita | 18000 | 2700 | 20700 | 45964
A3: =IF(B3<>"","LN"&ROW()-1,"") -> LN2 | B3: Linda Musita | C3: =IF(B3<>"",_xlfn.XLOOKUP(B3,'Client list'!B:B,'Client list'!A:A),"") -> Client2 | D3: 1100 | E3: 13 | F3: =IF(D3<>"",(D3+E3),"") -> 1113 | G3: 0 | H3: =IF(D3<>"",(D3*G3),"") -> 0 | I3: =IF(D3<>"",(D3+H3),"") -> 1100 | J3: 45952 | K3: =IF(D3<>"",(A3&" | "&B3&" | "&D3&" | "&H3&" | "&I3&" | "&J3),"") -> LN2 | Linda Musita | 1100 | 0 | 1100 | 45952
A4: =IF(B4<>"","LN"&ROW()-1,"") -> LN3 | B4: Linda Musita | C4: =IF(B4<>"",_xlfn.XLOOKUP(B4,'Client list'!B:B,'Client list'!A:A),"") -> Client2 | D4: 500 | E4: 7 | F4: =IF(D4<>"",(D4+E4),"") -> 507 | G4: 0 | H4: =IF(D4<>"",(D4*G4),"") -> 0 | I4: =IF(D4<>"",(D4+H4),"") -> 500 | J4: 45956 | K4: =IF(D4<>"",(A4&" | "&B4&" | "&D4&" | "&H4&" | "&I4&" | "&J4),"") -> LN3 | Linda Musita | 500 | 0 | 500 | 45956
A5: =IF(B5<>"","LN"&ROW()-1,"") -> LN4 | B5: Pauline Kayaja | C5: =IF(B5<>"",_xlfn.XLOOKUP(B5,'Client list'!B:B,'Client list'!A:A),"") -> Client3 | D5: 4000 | E5: 33 | F5: =IF(D5<>"",(D5+E5),"") -> 4033 | G5: 0.15 | H5: =IF(D5<>"",(D5*G5),"") -> 600 | I5: =IF(D5<>"",(D5+H5),"") -> 4600 | J5: 45757 | K5: =IF(D5<>"",(A5&" | "&B5&" | "&D5&" | "&H5&" | "&I5&" | "&J5),"") -> LN4 | Pauline Kayaja | 4000 | 600 | 4600 | 45757 | L5: Bad Debt
A6: =IF(B6<>"","LN"&ROW()-1,"") -> LN5 | B6: Tonny Ngaira | C6: =IF(B6<>"",_xlfn.XLOOKUP(B6,'Client list'!B:B,'Client list'!A:A),"") -> Client4 | D6: 1000 | E6: 13 | F6: =IF(D6<>"",(D6+E6),"") -> 1013 | G6: 0 | H6: =IF(D6<>"",(D6*G6),"") -> 0 | I6: =IF(D6<>"",(D6+H6),"") -> 1000 | J6: 45698 | K6: =IF(D6<>"",(A6&" | "&B6&" | "&D6&" | "&H6&" | "&I6&" | "&J6),"") -> LN5 | Tonny Ngaira | 1000 | 0 | 1000 | 45698 | L6: Bad Debt
A7: =IF(B7<>"","LN"&ROW()-1,"") -> LN6 | B7: James Nganga | C7: =IF(B7<>"",_xlfn.XLOOKUP(B7,'Client list'!B:B,'Client list'!A:A),"") -> Client5 | D7: 4000 | E7: 54 | F7: =IF(D7<>"",(D7+E7),"") -> 4054 | G7: 0.15 | H7: =IF(D7<>"",(D7*G7),"") -> 600 | I7: =IF(D7<>"",(D7+H7),"") -> 4600 | J7: 45964 | K7: =IF(D7<>"",(A7&" | "&B7&" | "&D7&" | "&H7&" | "&I7&" | "&J7),"") -> LN6 | James Nganga | 4000 | 600 | 4600 | 45964
A8: =IF(B8<>"","LN"&ROW()-1,"") -> LN7 | B8: Edmond Odongo | C8: =IF(B8<>"",_xlfn.XLOOKUP(B8,'Client list'!B:B,'Client list'!A:A),"") -> Client6 | D8: 5000 | E8: 57 | F8: =IF(D8<>"",(D8+E8),"") -> 5057 | G8: 0.15 | H8: =IF(D8<>"",(D8*G8),"") -> 750 | I8: =IF(D8<>"",(D8+H8),"") -> 5750 | J8: 45967 | K8: =IF(D8<>"",(A8&" | "&B8&" | "&D8&" | "&H8&" | "&I8&" | "&J8),"") -> LN7 | Edmond Odongo | 5000 | 750 | 5750 | 45967
A9: =IF(B9<>"","LN"&ROW()-1,"") -> LN8 | B9: Linda Musita | C9: =IF(B9<>"",_xlfn.XLOOKUP(B9,'Client list'!B:B,'Client list'!A:A),"") -> Client2 | D9: 2000 | E9: 29 | F9: =IF(D9<>"",(D9+E9),"") -> 2029 | G9: 0.15 | H9: =IF(D9<>"",(D9*G9),"") -> 300 | I9: =IF(D9<>"",(D9+H9),"") -> 2300 | J9: 45972 | K9: =IF(D9<>"",(A9&" | "&B9&" | "&D9&" | "&H9&" | "&I9&" | "&J9),"") -> LN8 | Linda Musita | 2000 | 300 | 2300 | 45972
A10: =IF(B10<>"","LN"&ROW()-1,"") -> LN9 | B10: Aluchio Caren | C10: =IF(B10<>"",_xlfn.XLOOKUP(B10,'Client list'!B:B,'Client list'!A:A),"") -> Client7 | D10: 1500 | E10: 29 | F10: =IF(D10<>"",(D10+E10),"") -> 1529 | G10: 0 | H10: =IF(D10<>"",(D10*G10),"") -> 0 | I10: =IF(D10<>"",(D10+H10),"") -> 1500 | J10: 45975 | K10: =IF(D10<>"",(A10&" | "&B10&" | "&D10&" | "&H10&" | "&I10&" | "&J10),"") -> LN9 | Aluchio Caren | 1500 | 0 | 1500 | 45975
A11: =IF(B11<>"","LN"&ROW()-1,"") -> LN10 | B11: James Nganga | C11: =IF(B11<>"",_xlfn.XLOOKUP(B11,'Client list'!B:B,'Client list'!A:A),"") -> Client5 | D11: 1000 | E11: 18 | F11: =IF(D11<>"",(D11+E11),"") -> 1018 | G11: 0.15 | H11: =IF(D11<>"",(D11*G11),"") -> 150 | I11: =IF(D11<>"",(D11+H11),"") -> 1150 | J11: 45981 | K11: =IF(D11<>"",(A11&" | "&B11&" | "&D11&" | "&H11&" | "&I11&" | "&J11),"") -> LN10 | James Nganga | 1000 | 150 | 1150 | 45981
A12: =IF(B12<>"","LN"&ROW()-1,"") -> LN11 | B12: Elvis Mbaya | C12: =IF(B12<>"",_xlfn.XLOOKUP(B12,'Client list'!B:B,'Client list'!A:A),"") -> Client1 | D12: 15000 | E12: 60 | F12: =IF(D12<>"",(D12+E12),"") -> 15060 | G12: 0.1 | H12: =IF(D12<>"",(D12*G12),"") -> 1500 | I12: =IF(D12<>"",(D12+H12),"") -> 16500 | J12: 45983 | K12: =IF(D12<>"",(A12&" | "&B12&" | "&D12&" | "&H12&" | "&I12&" | "&J12),"") -> LN11 | Elvis Mbaya | 15000 | 1500 | 16500 | 45983
A13: =IF(B13<>"","LN"&ROW()-1,"") -> LN12 | B13: Edmond Odongo | C13: =IF(B13<>"",_xlfn.XLOOKUP(B13,'Client list'!B:B,'Client list'!A:A),"") -> Client6 | D13: 5000 | E13: 57 | F13: =IF(D13<>"",(D13+E13),"") -> 5057 | G13: 0.15 | H13: =IF(D13<>"",(D13*G13),"") -> 750 | I13: =IF(D13<>"",(D13+H13),"") -> 5750 | J13: 45992 | K13: =IF(D13<>"",(A13&" | "&B13&" | "&D13&" | "&H13&" | "&I13&" | "&J13),"") -> LN12 | Edmond Odongo | 5000 | 750 | 5750 | 45992
A14: =IF(B14<>"","LN"&ROW()-1,"") -> LN13 | B14: James Nganga | C14: =IF(B14<>"",_xlfn.XLOOKUP(B14,'Client list'!B:B,'Client list'!A:A),"") -> Client5 | D14: 3000 | E14: 41 | F14: =IF(D14<>"",(D14+E14),"") -> 3041 | G14: 0.15 | H14: =IF(D14<>"",(D14*G14),"") -> 450 | I14: =IF(D14<>"",(D14+H14),"") -> 3450 | J14: 45993 | K14: =IF(D14<>"",(A14&" | "&B14&" | "&D14&" | "&H14&" | "&I14&" | "&J14),"") -> LN13 | James Nganga | 3000 | 450 | 3450 | 45993
A15: =IF(B15<>"","LN"&ROW()-1,"") -> LN14 | B15: Edmond Odongo | C15: =IF(B15<>"",_xlfn.XLOOKUP(B15,'Client list'!B:B,'Client list'!A:A),"") -> Client6 | D15: 2000 | E15: 28 | F15: =IF(D15<>"",(D15+E15),"") -> 2028 | G15: 0.15 | H15: =IF(D15<>"",(D15*G15),"") -> 300 | I15: =IF(D15<>"",(D15+H15),"") -> 2300 | J15: 45994 | K15: =IF(D15<>"",(A15&" | "&B15&" | "&D15&" | "&H15&" | "&I15&" | "&J15),"") -> LN14 | Edmond Odongo | 2000 | 300 | 2300 | 45994
A16: =IF(B16<>"","LN"&ROW()-1,"") -> LN15 | B16: Edmond Odongo | C16: =IF(B16<>"",_xlfn.XLOOKUP(B16,'Client list'!B:B,'Client list'!A:A),"") -> Client6 | D16: 7000 | E16: 0 | F16: =IF(D16<>"",(D16+E16),"") -> 7000 | G16: 0.15 | H16: =IF(D16<>"",(D16*G16),"") -> 1050 | I16: =IF(D16<>"",(D16+H16),"") -> 8050 | J16: 46015 | K16: =IF(D16<>"",(A16&" | "&B16&" | "&D16&" | "&H16&" | "&I16&" | "&J16),"") -> LN15 | Edmond Odongo | 7000 | 1050 | 8050 | 46015
A17: =IF(B17<>"","LN"&ROW()-1,"") -> LN16 | B17: James Nganga | C17: =IF(B17<>"",_xlfn.XLOOKUP(B17,'Client list'!B:B,'Client list'!A:A),"") -> Client5 | D17: 2000 | E17: 28 | F17: =IF(D17<>"",(D17+E17),"") -> 2028 | G17: 0.15 | H17: =IF(D17<>"",(D17*G17),"") -> 300 | I17: =IF(D17<>"",(D17+H17),"") -> 2300 | J17: 46020 | K17: =IF(D17<>"",(A17&" | "&B17&" | "&D17&" | "&H17&" | "&I17&" | "&J17),"") -> LN16 | James Nganga | 2000 | 300 | 2300 | 46020
A18: =IF(B18<>"","LN"&ROW()-1,"") -> LN17 | B18: Felicity | C18: =IF(B18<>"",_xlfn.XLOOKUP(B18,'Client list'!B:B,'Client list'!A:A),"") -> Client8 | D18: 1000 | E18: 13 | F18: =IF(D18<>"",(D18+E18),"") -> 1013 | G18: 0 | H18: =IF(D18<>"",(D18*G18),"") -> 0 | I18: =IF(D18<>"",(D18+H18),"") -> 1000 | J18: 45717 | K18: =IF(D18<>"",(A18&" | "&B18&" | "&D18&" | "&H18&" | "&I18&" | "&J18),"") -> LN17 | Felicity | 1000 | 0 | 1000 | 45717
... A20: =IF(B20<>"","LN"&ROW()-1,"") -> LN19 | B20: Edmond Odongo | C20: =IF(B20<>"",_xlfn.XLOOKUP(B20,'Client list'!B:B,'Client list'!A:A),"") -> Client6 | D20: 1000 | E20: 18 | F20: =IF(D20<>"",(D20+E20),"") -> 1018 | G20: 0.15 | H20: =IF(D20<>"",(D20*G20),"") -> 150 | I20: =IF(D20<>"",(D20+H20),"") -> 1150 | J20: 46039 | K20: =IF(D20<>"",(A20&" | "&B20&" | "&D20&" | "&H20&" | "&I20&" | "&J20),"") -> LN19 | Edmond Odongo | 1000 | 150 | 1150 | 46039
A21: =IF(B21<>"","LN"&ROW()-1,"") | C21: =IF(B21<>"",_xlfn.XLOOKUP(B21,'Client list'!B:B,'Client list'!A:A),"") | F21: =IF(D21<>"",(D21+E21),"") | H21: =IF(D21<>"",(D21*G21),"") | I21: =IF(D21<>"",(D21+H21),"") | K21: =IF(D21<>"",(A21&" | "&B21&" | "&D21&" | "&H21&" | "&I21&" | "&J21),"")
A22: =IF(B22<>"","LN"&ROW()-1,"") | C22: =IF(B22<>"",_xlfn.XLOOKUP(B22,'Client list'!B:B,'Client list'!A:A),"") | F22: =IF(D22<>"",(D22+E22),"") | H22: =IF(D22<>"",(D22*G22),"") | I22: =IF(D22<>"",(D22+H22),"") | K22: =IF(D22<>"",(A22&" | "&B22&" | "&D22&" | "&H22&" | "&I22&" | "&J22),"")
A23: =IF(B23<>"","LN"&ROW()-1,"") | C23: =IF(B23<>"",_xlfn.XLOOKUP(B23,'Client list'!B:B,'Client list'!A:A),"") | F23: =IF(D23<>"",(D23+E23),"") | H23: =IF(D23<>"",(D23*G23),"") | I23: =IF(D23<>"",(D23+H23),"") | K23: =IF(D23<>"",(A23&" | "&B23&" | "&D23&" | "&H23&" | "&I23&" | "&J23),"")
A24: =IF(B24<>"","LN"&ROW()-1,"") | C24: =IF(B24<>"",_xlfn.XLOOKUP(B24,'Client list'!B:B,'Client list'!A:A),"") | F24: =IF(D24<>"",(D24+E24),"") | H24: =IF(D24<>"",(D24*G24),"") | I24: =IF(D24<>"",(D24+H24),"") | K24: =IF(D24<>"",(A24&" | "&B24&" | "&D24&" | "&H24&" | "&I24&" | "&J24),"")
A25: =IF(B25<>"","LN"&ROW()-1,"") | C25: =IF(B25<>"",_xlfn.XLOOKUP(B25,'Client list'!B:B,'Client list'!A:A),"") | F25: =IF(D25<>"",(D25+E25),"") | H25: =IF(D25<>"",(D25*G25),"") | I25: =IF(D25<>"",(D25+H25),"") | K25: =IF(D25<>"",(A25&" | "&B25&" | "&D25&" | "&H25&" | "&I25&" | "&J25),"")
A26: =IF(B26<>"","LN"&ROW()-1,"") | C26: =IF(B26<>"",_xlfn.XLOOKUP(B26,'Client list'!B:B,'Client list'!A:A),"") | F26: =IF(D26<>"",(D26+E26),"") | H26: =IF(D26<>"",(D26*G26),"") | I26: =IF(D26<>"",(D26+H26),"") | K26: =IF(D26<>"",(A26&" | "&B26&" | "&D26&" | "&H26&" | "&I26&" | "&J26),"")
A27: =IF(B27<>"","LN"&ROW()-1,"") | C27: =IF(B27<>"",_xlfn.XLOOKUP(B27,'Client list'!B:B,'Client list'!A:A),"") | F27: =IF(D27<>"",(D27+E27),"") | H27: =IF(D27<>"",(D27*G27),"") | I27: =IF(D27<>"",(D27+H27),"") | K27: =IF(D27<>"",(A27&" | "&B27&" | "&D27&" | "&H27&" | "&I27&" | "&J27),"")
A28: =IF(B28<>"","LN"&ROW()-1,"") | C28: =IF(B28<>"",_xlfn.XLOOKUP(B28,'Client list'!B:B,'Client list'!A:A),"") | F28: =IF(D28<>"",(D28+E28),"") | H28: =IF(D28<>"",(D28*G28),"") | I28: =IF(D28<>"",(D28+H28),"") | K28: =IF(D28<>"",(A28&" | "&B28&" | "&D28&" | "&H28&" | "&I28&" | "&J28),"")
A29: =IF(B29<>"","LN"&ROW()-1,"") | C29: =IF(B29<>"",_xlfn.XLOOKUP(B29,'Client list'!B:B,'Client list'!A:A),"") | F29: =IF(D29<>"",(D29+E29),"") | H29: =IF(D29<>"",(D29*G29),"") | I29: =IF(D29<>"",(D29+H29),"") | K29: =IF(D29<>"",(A29&" | "&B29&" | "&D29&" | "&H29&" | "&I29&" | "&J29),"")
A30: =IF(B30<>"","LN"&ROW()-1,"") | C30: =IF(B30<>"",_xlfn.XLOOKUP(B30,'Client list'!B:B,'Client list'!A:A),"") | F30: =IF(D30<>"",(D30+E30),"") | H30: =IF(D30<>"",(D30*G30),"") | I30: =IF(D30<>"",(D30+H30),"") | K30: =IF(D30<>"",(A30&" | "&B30&" | "&D30&" | "&H30&" | "&I30&" | "&J30),"")
A31: =IF(B31<>"","LN"&ROW()-1,"") | C31: =IF(B31<>"",_xlfn.XLOOKUP(B31,'Client list'!B:B,'Client list'!A:A),"") | F31: =IF(D31<>"",(D31+E31),"") | H31: =IF(D31<>"",(D31*G31),"") | I31: =IF(D31<>"",(D31+H31),"") | K31: =IF(D31<>"",(A31&" | "&B31&" | "&D31&" | "&H31&" | "&I31&" | "&J31),"")
A32: =IF(B32<>"","LN"&ROW()-1,"") | C32: =IF(B32<>"",_xlfn.XLOOKUP(B32,'Client list'!B:B,'Client list'!A:A),"") | F32: =IF(D32<>"",(D32+E32),"") | H32: =IF(D32<>"",(D32*G32),"") | I32: =IF(D32<>"",(D32+H32),"") | K32: =IF(D32<>"",(A32&" | "&B32&" | "&D32&" | "&H32&" | "&I32&" | "&J32),"")
... A250: =IF(B250<>"","LN"&ROW()-1,"") | C250: =IF(B250<>"",_xlfn.XLOOKUP(B250,'Client list'!B:B,'Client list'!A:A),"") | F250: =IF(D250<>"",(D250+E250),"") | H250: =IF(D250<>"",(D250*G250),"") | I250: =IF(D250<>"",(D250+H250),"") | K250: =IF(D250<>"",(A250&" | "&B250&" | "&D250&" | "&H250&" | "&I250&" | "&J250),"")
I251: =IF(D251<>"",(D251+H251),"")

Sheet Payments
A1: Payment ID | B1: Lookcol1 | C1: Loan ID | D1: Client Name | E1: Expected Amnt | F1: Date of remittance | G1: Amount Paid
A2: =IF(B2<>"","P"&ROW()-1,"") -> P1 | B2: LN4 | Pauline Kayaja | 4000 | 600 | 4600 | 45757 | C2: =IF(B2<>"",(LEFT(B2,FIND(" |",B2)-1)),"") -> LN4 | D2: =IF(C2<>"",(_xlfn.XLOOKUP(C2,'Loan Out'!A:A,'Loan Out'!B:B)),"") -> Pauline Kayaja | E2: =IF(B2<>"",(_xlfn.XLOOKUP(C2,'Loan Out'!A:A,'Loan Out'!I:I)),"") -> 4600 | F2: 45869 | G2: 3000
A3: =IF(B3<>"","P"&ROW()-1,"") -> P2 | B3: LN6 | James Nganga | 4000 | 600 | 4600 | 45964 | C3: =IF(B3<>"",(LEFT(B3,FIND(" |",B3)-1)),"") -> LN6 | D3: =IF(C3<>"",(_xlfn.XLOOKUP(C3,'Loan Out'!A:A,'Loan Out'!B:B)),"") -> James Nganga | E3: =IF(B3<>"",(_xlfn.XLOOKUP(C3,'Loan Out'!A:A,'Loan Out'!I:I)),"") -> 4600 | F3: 45991 | G3: 4600
A4: =IF(B4<>"","P"&ROW()-1,"") -> P3 | B4: LN7 | Edmond Odongo | 5000 | 750 | 5750 | 45967 | C4: =IF(B4<>"",(LEFT(B4,FIND(" |",B4)-1)),"") -> LN7 | D4: =IF(C4<>"",(_xlfn.XLOOKUP(C4,'Loan Out'!A:A,'Loan Out'!B:B)),"") -> Edmond Odongo | E4: =IF(B4<>"",(_xlfn.XLOOKUP(C4,'Loan Out'!A:A,'Loan Out'!I:I)),"") -> 5750 | F4: 45991 | G4: 5750
A5: =IF(B5<>"","P"&ROW()-1,"") -> P4 | B5: LN9 | Aluchio Caren | 1500 | 0 | 1500 | 45975 | C5: =IF(B5<>"",(LEFT(B5,FIND(" |",B5)-1)),"") -> LN9 | D5: =IF(C5<>"",(_xlfn.XLOOKUP(C5,'Loan Out'!A:A,'Loan Out'!B:B)),"") -> Aluchio Caren | E5: =IF(B5<>"",(_xlfn.XLOOKUP(C5,'Loan Out'!A:A,'Loan Out'!I:I)),"") -> 1500 | F5: 45996 | G5: 1600
A6: =IF(B6<>"","P"&ROW()-1,"") -> P5 | B6: LN10 | James Nganga | 1000 | 150 | 1150 | 45981 | C6: =IF(B6<>"",(LEFT(B6,FIND(" |",B6)-1)),"") -> LN10 | D6: =IF(C6<>"",(_xlfn.XLOOKUP(C6,'Loan Out'!A:A,'Loan Out'!B:B)),"") -> James Nganga | E6: =IF(B6<>"",(_xlfn.XLOOKUP(C6,'Loan Out'!A:A,'Loan Out'!I:I)),"") -> 1150 | F6: 45991 | G6: 1150
A7: =IF(B7<>"","P"&ROW()-1,"") -> P6 | B7: LN11 | Elvis Mbaya | 15000 | 1500 | 16500 | 45983 | C7: =IF(B7<>"",(LEFT(B7,FIND(" |",B7)-1)),"") -> LN11 | D7: =IF(C7<>"",(_xlfn.XLOOKUP(C7,'Loan Out'!A:A,'Loan Out'!B:B)),"") -> Elvis Mbaya | E7: =IF(B7<>"",(_xlfn.XLOOKUP(C7,'Loan Out'!A:A,'Loan Out'!I:I)),"") -> 16500 | F7: 45991 | G7: 10000
A8: =IF(B8<>"","P"&ROW()-1,"") -> P7 | B8: LN12 | Edmond Odongo | 5000 | 750 | 5750 | 45992 | C8: =IF(B8<>"",(LEFT(B8,FIND(" |",B8)-1)),"") -> LN12 | D8: =IF(C8<>"",(_xlfn.XLOOKUP(C8,'Loan Out'!A:A,'Loan Out'!B:B)),"") -> Edmond Odongo | E8: =IF(B8<>"",(_xlfn.XLOOKUP(C8,'Loan Out'!A:A,'Loan Out'!I:I)),"") -> 5750 | F8: 46015 | G8: 5750
A9: =IF(B9<>"","P"&ROW()-1,"") -> P8 | B9: LN13 | James Nganga | 3000 | 450 | 3450 | 45993 | C9: =IF(B9<>"",(LEFT(B9,FIND(" |",B9)-1)),"") -> LN13 | D9: =IF(C9<>"",(_xlfn.XLOOKUP(C9,'Loan Out'!A:A,'Loan Out'!B:B)),"") -> James Nganga | E9: =IF(B9<>"",(_xlfn.XLOOKUP(C9,'Loan Out'!A:A,'Loan Out'!I:I)),"") -> 3450 | F9: 46015 | G9: 3450
A10: =IF(B10<>"","P"&ROW()-1,"") -> P9 | B10: LN14 | Edmond Odongo | 2000 | 300 | 2300 | 45994 | C10: =IF(B10<>"",(LEFT(B10,FIND(" |",B10)-1)),"") -> LN14 | D10: =IF(C10<>"",(_xlfn.XLOOKUP(C10,'Loan Out'!A:A,'Loan Out'!B:B)),"") -> Edmond Odongo | E10: =IF(B10<>"",(_xlfn.XLOOKUP(C10,'Loan Out'!A:A,'Loan Out'!I:I)),"") -> 2300 | F10: 46015 | G10: 2300
A11: =IF(B11<>"","P"&ROW()-1,"") -> P10 | B11: LN17 | Felicity | 1000 | 0 | 1000 | 45717 | C11: =IF(B11<>"",(LEFT(B11,FIND(" |",B11)-1)),"") -> LN17 | D11: =IF(C11<>"",(_xlfn.XLOOKUP(C11,'Loan Out'!A:A,'Loan Out'!B:B)),"") -> Felicity | E11: =IF(B11<>"",(_xlfn.XLOOKUP(C11,'Loan Out'!A:A,'Loan Out'!I:I)),"") -> 1000 | F11: 46038 | G11: 1000
A12: =IF(B12<>"","P"&ROW()-1,"") | C12: =IF(B12<>"",(LEFT(B12,FIND(" |",B12)-1)),"") | D12: =IF(C12<>"",(_xlfn.XLOOKUP(C12,'Loan Out'!A:A,'Loan Out'!B:B)),"") | E12: =IF(B12<>"",(_xlfn.XLOOKUP(C12,'Loan Out'!A:A,'Loan Out'!I:I)),"")
A13: =IF(B13<>"","P"&ROW()-1,"") | C13: =IF(B13<>"",(LEFT(B13,FIND(" |",B13)-1)),"") | D13: =IF(C13<>"",(_xlfn.XLOOKUP(C13,'Loan Out'!A:A,'Loan Out'!B:B)),"") | E13: =IF(B13<>"",(_xlfn.XLOOKUP(C13,'Loan Out'!A:A,'Loan Out'!I:I)),"")
A14: =IF(B14<>"","P"&ROW()-1,"") | C14: =IF(B14<>"",(LEFT(B14,FIND(" |",B14)-1)),"") | D14: =IF(C14<>"",(_xlfn.XLOOKUP(C14,'Loan Out'!A:A,'Loan Out'!B:B)),"") | E14: =IF(B14<>"",(_xlfn.XLOOKUP(C14,'Loan Out'!A:A,'Loan Out'!I:I)),"")
A15: =IF(B15<>"","P"&ROW()-1,"") | C15: =IF(B15<>"",(LEFT(B15,FIND(" |",B15)-1)),"") | D15: =IF(C15<>"",(_xlfn.XLOOKUP(C15,'Loan Out'!A:A,'Loan Out'!B:B)),"") | E15: =IF(B15<>"",(_xlfn.XLOOKUP(C15,'Loan Out'!A:A,'Loan Out'!I:I)),"")
A16: =IF(B16<>"","P"&ROW()-1,"") | C16: =IF(B16<>"",(LEFT(B16,FIND(" |",B16)-1)),"") | D16: =IF(C16<>"",(_xlfn.XLOOKUP(C16,'Loan Out'!A:A,'Loan Out'!B:B)),"") | E16: =IF(B16<>"",(_xlfn.XLOOKUP(C16,'Loan Out'!A:A,'Loan Out'!I:I)),"")
A17: =IF(B17<>"","P"&ROW()-1,"") | C17: =IF(B17<>"",(LEFT(B17,FIND(" |",B17)-1)),"") | D17: =IF(C17<>"",(_xlfn.XLOOKUP(C17,'Loan Out'!A:A,'Loan Out'!B:B)),"") | E17: =IF(B17<>"",(_xlfn.XLOOKUP(C17,'Loan Out'!A:A,'Loan Out'!I:I)),"")
A18: =IF(B18<>"","P"&ROW()-1,"") | C18: =IF(B18<>"",(LEFT(B18,FIND(" |",B18)-1)),"") | D18: =IF(C18<>"",(_xlfn.XLOOKUP(C18,'Loan Out'!A:A,'Loan Out'!B:B)),"") | E18: =IF(B18<>"",(_xlfn.XLOOKUP(C18,'Loan Out'!A:A,'Loan Out'!I:I)),"")
A19: =IF(B19<>"","P"&ROW()-1,"") | C19: =IF(B19<>"",(LEFT(B19,FIND(" |",B19)-1)),"") | D19: =IF(C19<>"",(_xlfn.XLOOKUP(C19,'Loan Out'!A:A,'Loan Out'!B:B)),"") | E19: =IF(B19<>"",(_xlfn.XLOOKUP(C19,'Loan Out'!A:A,'Loan Out'!I:I)),"")
A20: =IF(B20<>"","P"&ROW()-1,"") | C20: =IF(B20<>"",(LEFT(B20,FIND(" |",B20)-1)),"") | D20: =IF(C20<>"",(_xlfn.XLOOKUP(C20,'Loan Out'!A:A,'Loan Out'!B:B)),"") | E20: =IF(B20<>"",(_xlfn.XLOOKUP(C20,'Loan Out'!A:A,'Loan Out'!I:I)),"")
A21: =IF(B21<>"","P"&ROW()-1,"") | C21: =IF(B21<>"",(LEFT(B21,FIND(" |",B21)-1)),"") | D21: =IF(C21<>"",(_xlfn.XLOOKUP(C21,'Loan Out'!A:A,'Loan Out'!B:B)),"") | E21: =IF(B21<>"",(_xlfn.XLOOKUP(C21,'Loan Out'!A:A,'Loan Out'!I:I)),"")
A22: =IF(B22<>"","P"&ROW()-1,"") | C22: =IF(B22<>"",(LEFT(B22,FIND(" |",B22)-1)),"") | D22: =IF(C22<>"",(_xlfn.XLOOKUP(C22,'Loan Out'!A:A,'Loan Out'!B:B)),"") | E22: =IF(B22<>"",(_xlfn.XLOOKUP(C22,'Loan Out'!A:A,'Loan Out'!I:I)),"")
A23: =IF(B23<>"","P"&ROW()-1,"") | C23: =IF(B23<>"",(LEFT(B23,FIND(" |",B23)-1)),"") | D23: =IF(C23<>"",(_xlfn.XLOOKUP(C23,'Loan Out'!A:A,'Loan Out'!B:B)),"") | E23: =IF(B23<>"",(_xlfn.XLOOKUP(C23,'Loan Out'!A:A,'Loan Out'!I:I)),"")
... A220: =IF(B220<>"","P"&ROW()-1,"") | C220: =IF(B220<>"",(LEFT(B220,FIND(" |",B220)-1)),"") | D220: =IF(C220<>"",(_xlfn.XLOOKUP(C220,'Loan Out'!A:A,'Loan Out'!B:B)),"") | E220: =IF(B220<>"",(_xlfn.XLOOKUP(C220,'Loan Out'!A:A,'Loan Out'!I:I)),"")
A221: =IF(B221<>"","LN"&ROW()-1,"") | C221: =IF(B221<>"",(LEFT(B221,FIND(" |",B221)-1)),"") | D221: =IF(C221<>"",(_xlfn.XLOOKUP(C221,'Loan Out'!A:A,'Loan Out'!B:B)),"") | E221: =IF(B221<>"",(_xlfn.XLOOKUP(C221,'Loan Out'!A:A,'Loan Out'!I:I)),"")
A222: =IF(B222<>"","LN"&ROW()-1,"") | C222: =IF(B222<>"",(LEFT(B222,FIND(" |",B222)-1)),"") | D222: =IF(C222<>"",(_xlfn.XLOOKUP(C222,'Loan Out'!A:A,'Loan Out'!B:B)),"") | E222: =IF(B222<>"",(_xlfn.XLOOKUP(C222,'Loan Out'!A:A,'Loan Out'!I:I)),"")
A223: =IF(B223<>"","LN"&ROW()-1,"") | C223: =IF(B223<>"",(LEFT(B223,FIND(" |",B223)-1)),"") | D223: =IF(C223<>"",(_xlfn.XLOOKUP(C223,'Loan Out'!A:A,'Loan Out'!B:B)),"") | E223: =IF(B223<>"",(_xlfn.XLOOKUP(C223,'Loan Out'!A:A,'Loan Out'!I:I)),"")
A224: =IF(B224<>"","LN"&ROW()-1,"") | C224: =IF(B224<>"",(LEFT(B224,FIND(" |",B224)-1)),"") | D224: =IF(C224<>"",(_xlfn.XLOOKUP(C224,'Loan Out'!A:A,'Loan Out'!B:B)),"") | E224: =IF(B224<>"",(_xlfn.XLOOKUP(C224,'Loan Out'!A:A,'Loan Out'!I:I)),"")
A225: =IF(B225<>"","LN"&ROW()-1,"") | C225: =IF(B225<>"",(LEFT(B225,FIND(" |",B225)-1)),"") | D225: =IF(C225<>"",(_xlfn.XLOOKUP(C225,'Loan Out'!A:A,'Loan Out'!B:B)),"") | E225: =IF(B225<>"",(_xlfn.XLOOKUP(C225,'Loan Out'!A:A,'Loan Out'!I:I)),"")
A226: =IF(B226<>"","LN"&ROW()-1,"") | C226: =IF(B226<>"",(LEFT(B226,FIND(" |",B226)-1)),"") | D226: =IF(C226<>"",(_xlfn.XLOOKUP(C226,'Loan Out'!A:A,'Loan Out'!B:B)),"") | E226: =IF(B226<>"",(_xlfn.XLOOKUP(C226,'Loan Out'!A:A,'Loan Out'!I:I)),"")
A227: =IF(B227<>"","LN"&ROW()-1,"") | C227: =IF(B227<>"",(LEFT(B227,FIND(" |",B227)-1)),"") | D227: =IF(C227<>"",(_xlfn.XLOOKUP(C227,'Loan Out'!A:A,'Loan Out'!B:B)),"") | E227: =IF(B227<>"",(_xlfn.XLOOKUP(C227,'Loan Out'!A:A,'Loan Out'!I:I)),"")
A228: =IF(B228<>"","LN"&ROW()-1,"") | C228: =IF(B228<>"",(LEFT(B228,FIND(" |",B228)-1)),"") | D228: =IF(C228<>"",(_xlfn.XLOOKUP(C228,'Loan Out'!A:A,'Loan Out'!B:B)),"") | E228: =IF(B228<>"",(_xlfn.XLOOKUP(C228,'Loan Out'!A:A,'Loan Out'!I:I)),"")
A229: =IF(B229<>"","LN"&ROW()-1,"") | C229: =IF(B229<>"",(LEFT(B229,FIND(" |",B229)-1)),"") | D229: =IF(C229<>"",(_xlfn.XLOOKUP(C229,'Loan Out'!A:A,'Loan Out'!B:B)),"") | E229: =IF(B229<>"",(_xlfn.XLOOKUP(C229,'Loan Out'!A:A,'Loan Out'!I:I)),"")
A230: =IF(B230<>"","LN"&ROW()-1,"") | C230: =IF(B230<>"",(LEFT(B230,FIND(" |",B230)-1)),"") | D230: =IF(C230<>"",(_xlfn.XLOOKUP(C230,'Loan Out'!A:A,'Loan Out'!B:B)),"") | E230: =IF(B230<>"",(_xlfn.XLOOKUP(C230,'Loan Out'!A:A,'Loan Out'!I:I)),"")
A231: =IF(B231<>"","LN"&ROW()-1,"") | C231: =IF(B231<>"",(LEFT(B231,FIND(" |",B231)-1)),"") | D231: =IF(C231<>"",(_xlfn.XLOOKUP(C231,'Loan Out'!A:A,'Loan Out'!B:B)),"") | E231: =IF(B231<>"",(_xlfn.XLOOKUP(C231,'Loan Out'!A:A,'Loan Out'!I:I)),"")
A232: =IF(B232<>"","LN"&ROW()-1,"") | C232: =IF(B232<>"",(LEFT(B232,FIND(" |",B232)-1)),"") | D232: =IF(C232<>"",(_xlfn.XLOOKUP(C232,'Loan Out'!A:A,'Loan Out'!B:B)),"") | E232: =IF(B232<>"",(_xlfn.XLOOKUP(C232,'Loan Out'!A:A,'Loan Out'!I:I)),"")
... A250: =IF(B250<>"","LN"&ROW()-1,"") | C250: =IF(B250<>"",(LEFT(B250,FIND(" |",B250)-1)),"") | D250: =IF(C250<>"",(_xlfn.XLOOKUP(C250,'Loan Out'!A:A,'Loan Out'!B:B)),"") | E250: =IF(B250<>"",(_xlfn.XLOOKUP(C250,'Loan Out'!A:A,'Loan Out'!I:I)),"")

Sheet Records
A1: Transaction ID | B1: Lookcol | C1: LOAN ID | D1: Date | E1: Principal Amount | F1: Transaction cost | G1: Principal + Other costs | H1: Rate | I1: Interest | J1: Expected Amnt | K1: Loan Date | L1: Remittance Amount | M1: Unpaid Amount | N1: Profit | O1: Loss | P1: Loan Status
A2: =IF(C2<>"","Entry"&ROW()-1,"") -> Entry1 | B2: LN1 | Linda Musita | 18000 | 2700 | 20700 | 45964 | C2: =IF(B2<>"",(LEFT(B2,FIND(" |",B2)-1)),"") -> LN1 | D2: =IF(C2="","",(_xlfn.XLOOKUP(C2,'Loan Out'!A:A,'Loan Out'!J:J))) -> 45964 | E2: =IF(C2="","",(_xlfn.XLOOKUP(C2,'Loan Out'!A:A,'Loan Out'!D:D))) -> 18000 | F2: =IF(C2="","",(_xlfn.XLOOKUP(C2,'Loan Out'!A:A,'Loan Out'!E:E))) -> 105 | G2: =IF(C2="","",(_xlfn.XLOOKUP(C2,'Loan Out'!A:A,'Loan Out'!F:F))) -> 18105 | H2: =IF(C2="","",(_xlfn.XLOOKUP(C2,'Loan Out'!A:A,'Loan Out'!G:G))) -> 0.15 | I2: =IF(C2="","",(_xlfn.XLOOKUP(C2,'Loan Out'!A:A,'Loan Out'!H:H))) -> 2700 | J2: =IF(C2="","",(_xlfn.XLOOKUP(C2,'Loan Out'!A:A,'Loan Out'!I:I))) -> 20700 | K2: =IF(C2="","",(_xlfn.XLOOKUP(C2,'Loan Out'!A:A,'Loan Out'!J:J))) -> 45964 | L2: =IF(C2<>"",(SUMIF(Payments!C:C,C2,Payments!G:G)),"") -> 0 | M2: =IF(C2<>"",(J2-L2),"") -> 20700 | N2: =IF(B2<>"",(IF(L2>G2,(L2-G2),0)),"") -> 0 | O2: =IF(B2<>"",(IF(P2="Bad debt",M2,0)),"") -> 0 | P2: =IF(B2<>"",(IF((_xlfn.XLOOKUP(C2,'Loan Out'!A:A,'Loan Out'!L:L))="Bad debt","Bad debt",IF(M2>0,"Pending","Settled"))),"") -> Pending
A3: =IF(C3<>"","Entry"&ROW()-1,"") -> Entry2 | B3: LN2 | Linda Musita | 1100 | 0 | 1100 | 45952 | C3: =IF(B3<>"",(LEFT(B3,FIND(" |",B3)-1)),"") -> LN2 | D3: =IF(C3="","",(_xlfn.XLOOKUP(C3,'Loan Out'!A:A,'Loan Out'!J:J))) -> 45952 | E3: =IF(C3="","",(_xlfn.XLOOKUP(C3,'Loan Out'!A:A,'Loan Out'!D:D))) -> 1100 | F3: =IF(C3="","",(_xlfn.XLOOKUP(C3,'Loan Out'!A:A,'Loan Out'!E:E))) -> 13 | G3: =IF(C3="","",(_xlfn.XLOOKUP(C3,'Loan Out'!A:A,'Loan Out'!F:F))) -> 1113 | H3: =IF(C3="","",(_xlfn.XLOOKUP(C3,'Loan Out'!A:A,'Loan Out'!G:G))) -> 0 | I3: =IF(C3="","",(_xlfn.XLOOKUP(C3,'Loan Out'!A:A,'Loan Out'!H:H))) -> 0 | J3: =IF(C3="","",(_xlfn.XLOOKUP(C3,'Loan Out'!A:A,'Loan Out'!I:I))) -> 1100 | K3: =IF(C3="","",(_xlfn.XLOOKUP(C3,'Loan Out'!A:A,'Loan Out'!J:J))) -> 45952 | L3: =IF(C3<>"",(SUMIF(Payments!C:C,C3,Payments!G:G)),"") -> 0 | M3: =IF(C3<>"",(J3-L3),"") -> 1100 | N3: =IF(B3<>"",(IF(L3>G3,(L3-G3),0)),"") -> 0 | O3: =IF(B3<>"",(IF(P3="Bad debt",M3,0)),"") -> 0 | P3: =IF(B3<>"",(IF((_xlfn.XLOOKUP(C3,'Loan Out'!A:A,'Loan Out'!L:L))="Bad debt","Bad debt",IF(M3>0,"Pending","Settled"))),"") -> Pending
A4: =IF(C4<>"","Entry"&ROW()-1,"") -> Entry3 | B4: LN3 | Linda Musita | 500 | 0 | 500 | 45956 | C4: =IF(B4<>"",(LEFT(B4,FIND(" |",B4)-1)),"") -> LN3 | D4: =IF(C4="","",(_xlfn.XLOOKUP(C4,'Loan Out'!A:A,'Loan Out'!J:J))) -> 45956 | E4: =IF(C4="","",(_xlfn.XLOOKUP(C4,'Loan Out'!A:A,'Loan Out'!D:D))) -> 500 | F4: =IF(C4="","",(_xlfn.XLOOKUP(C4,'Loan Out'!A:A,'Loan Out'!E:E))) -> 7 | G4: =IF(C4="","",(_xlfn.XLOOKUP(C4,'Loan Out'!A:A,'Loan Out'!F:F))) -> 507 | H4: =IF(C4="","",(_xlfn.XLOOKUP(C4,'Loan Out'!A:A,'Loan Out'!G:G))) -> 0 | I4: =IF(C4="","",(_xlfn.XLOOKUP(C4,'Loan Out'!A:A,'Loan Out'!H:H))) -> 0 | J4: =IF(C4="","",(_xlfn.XLOOKUP(C4,'Loan Out'!A:A,'Loan Out'!I:I))) -> 500 | K4: =IF(C4="","",(_xlfn.XLOOKUP(C4,'Loan Out'!A:A,'Loan Out'!J:J))) -> 45956 | L4: =IF(C4<>"",(SUMIF(Payments!C:C,C4,Payments!G:G)),"") -> 0 | M4: =IF(C4<>"",(J4-L4),"") -> 500 | N4: =IF(B4<>"",(IF(L4>G4,(L4-G4),0)),"") -> 0 | O4: =IF(B4<>"",(IF(P4="Bad debt",M4,0)),"") -> 0 | P4: =IF(B4<>"",(IF((_xlfn.XLOOKUP(C4,'Loan Out'!A:A,'Loan Out'!L:L))="Bad debt","Bad debt",IF(M4>0,"Pending","Settled"))),"") -> Pending
A5: =IF(C5<>"","Entry"&ROW()-1,"") -> Entry4 | B5: LN4 | Pauline Kayaja | 4000 | 600 | 4600 | 45757 | C5: =IF(B5<>"",(LEFT(B5,FIND(" |",B5)-1)),"") -> LN4 | D5: =IF(C5="","",(_xlfn.XLOOKUP(C5,'Loan Out'!A:A,'Loan Out'!J:J))) -> 45757 | E5: =IF(C5="","",(_xlfn.XLOOKUP(C5,'Loan Out'!A:A,'Loan Out'!D:D))) -> 4000 | F5: =IF(C5="","",(_xlfn.XLOOKUP(C5,'Loan Out'!A:A,'Loan Out'!E:E))) -> 33 | G5: =IF(C5="","",(_xlfn.XLOOKUP(C5,'Loan Out'!A:A,'Loan Out'!F:F))) -> 4033 | H5: =IF(C5="","",(_xlfn.XLOOKUP(C5,'Loan Out'!A:A,'Loan Out'!G:G))) -> 0.15 | I5: =IF(C5="","",(_xlfn.XLOOKUP(C5,'Loan Out'!A:A,'Loan Out'!H:H))) -> 600 | J5: =IF(C5="","",(_xlfn.XLOOKUP(C5,'Loan Out'!A:A,'Loan Out'!I:I))) -> 4600 | K5: =IF(C5="","",(_xlfn.XLOOKUP(C5,'Loan Out'!A:A,'Loan Out'!J:J))) -> 45757 | L5: =IF(C5<>"",(SUMIF(Payments!C:C,C5,Payments!G:G)),"") -> 3000 | M5: =IF(C5<>"",(J5-L5),"") -> 1600 | N5: =IF(B5<>"",(IF(L5>G5,(L5-G5),0)),"") -> 0 | O5: =IF(B5<>"",(IF(P5="Bad debt",M5,0)),"") -> 1600 | P5: =IF(B5<>"",(IF((_xlfn.XLOOKUP(C5,'Loan Out'!A:A,'Loan Out'!L:L))="Bad debt","Bad debt",IF(M5>0,"Pending","Settled"))),"") -> Bad debt
A6: =IF(C6<>"","Entry"&ROW()-1,"") -> Entry5 | B6: LN5 | Tonny Ngaira | 1000 | 0 | 1000 | 45698 | C6: =IF(B6<>"",(LEFT(B6,FIND(" |",B6)-1)),"") -> LN5 | D6: =IF(C6="","",(_xlfn.XLOOKUP(C6,'Loan Out'!A:A,'Loan Out'!J:J))) -> 45698 | E6: =IF(C6="","",(_xlfn.XLOOKUP(C6,'Loan Out'!A:A,'Loan Out'!D:D))) -> 1000 | F6: =IF(C6="","",(_xlfn.XLOOKUP(C6,'Loan Out'!A:A,'Loan Out'!E:E))) -> 13 | G6: =IF(C6="","",(_xlfn.XLOOKUP(C6,'Loan Out'!A:A,'Loan Out'!F:F))) -> 1013 | H6: =IF(C6="","",(_xlfn.XLOOKUP(C6,'Loan Out'!A:A,'Loan Out'!G:G))) -> 0 | I6: =IF(C6="","",(_xlfn.XLOOKUP(C6,'Loan Out'!A:A,'Loan Out'!H:H))) -> 0 | J6: =IF(C6="","",(_xlfn.XLOOKUP(C6,'Loan Out'!A:A,'Loan Out'!I:I))) -> 1000 | K6: =IF(C6="","",(_xlfn.XLOOKUP(C6,'Loan Out'!A:A,'Loan Out'!J:J))) -> 45698 | L6: =IF(C6<>"",(SUMIF(Payments!C:C,C6,Payments!G:G)),"") -> 0 | M6: =IF(C6<>"",(J6-L6),"") -> 1000 | N6: =IF(B6<>"",(IF(L6>G6,(L6-G6),0)),"") -> 0 | O6: =IF(B6<>"",(IF(P6="Bad debt",M6,0)),"") -> 1000 | P6: =IF(B6<>"",(IF((_xlfn.XLOOKUP(C6,'Loan Out'!A:A,'Loan Out'!L:L))="Bad debt","Bad debt",IF(M6>0,"Pending","Settled"))),"") -> Bad debt
A7: =IF(C7<>"","Entry"&ROW()-1,"") -> Entry6 | B7: LN6 | James Nganga | 4000 | 600 | 4600 | 45964 | C7: =IF(B7<>"",(LEFT(B7,FIND(" |",B7)-1)),"") -> LN6 | D7: =IF(C7="","",(_xlfn.XLOOKUP(C7,'Loan Out'!A:A,'Loan Out'!J:J))) -> 45964 | E7: =IF(C7="","",(_xlfn.XLOOKUP(C7,'Loan Out'!A:A,'Loan Out'!D:D))) -> 4000 | F7: =IF(C7="","",(_xlfn.XLOOKUP(C7,'Loan Out'!A:A,'Loan Out'!E:E))) -> 54 | G7: =IF(C7="","",(_xlfn.XLOOKUP(C7,'Loan Out'!A:A,'Loan Out'!F:F))) -> 4054 | H7: =IF(C7="","",(_xlfn.XLOOKUP(C7,'Loan Out'!A:A,'Loan Out'!G:G))) -> 0.15 | I7: =IF(C7="","",(_xlfn.XLOOKUP(C7,'Loan Out'!A:A,'Loan Out'!H:H))) -> 600 | J7: =IF(C7="","",(_xlfn.XLOOKUP(C7,'Loan Out'!A:A,'Loan Out'!I:I))) -> 4600 | K7: =IF(C7="","",(_xlfn.XLOOKUP(C7,'Loan Out'!A:A,'Loan Out'!J:J))) -> 45964 | L7: =IF(C7<>"",(SUMIF(Payments!C:C,C7,Payments!G:G)),"") -> 4600 | M7: =IF(C7<>"",(J7-L7),"") -> 0 | N7: =IF(B7<>"",(IF(L7>G7,(L7-G7),0)),"") -> 546 | O7: =IF(B7<>"",(IF(P7="Bad debt",M7,0)),"") -> 0 | P7: =IF(B7<>"",(IF((_xlfn.XLOOKUP(C7,'Loan Out'!A:A,'Loan Out'!L:L))="Bad debt","Bad debt",IF(M7>0,"Pending","Settled"))),"") -> Settled
A8: =IF(C8<>"","Entry"&ROW()-1,"") -> Entry7 | B8: LN7 | Edmond Odongo | 5000 | 750 | 5750 | 45967 | C8: =IF(B8<>"",(LEFT(B8,FIND(" |",B8)-1)),"") -> LN7 | D8: =IF(C8="","",(_xlfn.XLOOKUP(C8,'Loan Out'!A:A,'Loan Out'!J:J))) -> 45967 | E8: =IF(C8="","",(_xlfn.XLOOKUP(C8,'Loan Out'!A:A,'Loan Out'!D:D))) -> 5000 | F8: =IF(C8="","",(_xlfn.XLOOKUP(C8,'Loan Out'!A:A,'Loan Out'!E:E))) -> 57 | G8: =IF(C8="","",(_xlfn.XLOOKUP(C8,'Loan Out'!A:A,'Loan Out'!F:F))) -> 5057 | H8: =IF(C8="","",(_xlfn.XLOOKUP(C8,'Loan Out'!A:A,'Loan Out'!G:G))) -> 0.15 | I8: =IF(C8="","",(_xlfn.XLOOKUP(C8,'Loan Out'!A:A,'Loan Out'!H:H))) -> 750 | J8: =IF(C8="","",(_xlfn.XLOOKUP(C8,'Loan Out'!A:A,'Loan Out'!I:I))) -> 5750 | K8: =IF(C8="","",(_xlfn.XLOOKUP(C8,'Loan Out'!A:A,'Loan Out'!J:J))) -> 45967 | L8: =IF(C8<>"",(SUMIF(Payments!C:C,C8,Payments!G:G)),"") -> 5750 | M8: =IF(C8<>"",(J8-L8),"") -> 0 | N8: =IF(B8<>"",(IF(L8>G8,(L8-G8),0)),"") -> 693 | O8: =IF(B8<>"",(IF(P8="Bad debt",M8,0)),"") -> 0 | P8: =IF(B8<>"",(IF((_xlfn.XLOOKUP(C8,'Loan Out'!A:A,'Loan Out'!L:L))="Bad debt","Bad debt",IF(M8>0,"Pending","Settled"))),"") -> Settled
A9: =IF(C9<>"","Entry"&ROW()-1,"") -> Entry8 | B9: LN8 | Linda Musita | 2000 | 300 | 2300 | 45972 | C9: =IF(B9<>"",(LEFT(B9,FIND(" |",B9)-1)),"") -> LN8 | D9: =IF(C9="","",(_xlfn.XLOOKUP(C9,'Loan Out'!A:A,'Loan Out'!J:J))) -> 45972 | E9: =IF(C9="","",(_xlfn.XLOOKUP(C9,'Loan Out'!A:A,'Loan Out'!D:D))) -> 2000 | F9: =IF(C9="","",(_xlfn.XLOOKUP(C9,'Loan Out'!A:A,'Loan Out'!E:E))) -> 29 | G9: =IF(C9="","",(_xlfn.XLOOKUP(C9,'Loan Out'!A:A,'Loan Out'!F:F))) -> 2029 | H9: =IF(C9="","",(_xlfn.XLOOKUP(C9,'Loan Out'!A:A,'Loan Out'!G:G))) -> 0.15 | I9: =IF(C9="","",(_xlfn.XLOOKUP(C9,'Loan Out'!A:A,'Loan Out'!H:H))) -> 300 | J9: =IF(C9="","",(_xlfn.XLOOKUP(C9,'Loan Out'!A:A,'Loan Out'!I:I))) -> 2300 | K9: =IF(C9="","",(_xlfn.XLOOKUP(C9,'Loan Out'!A:A,'Loan Out'!J:J))) -> 45972 | L9: =IF(C9<>"",(SUMIF(Payments!C:C,C9,Payments!G:G)),"") -> 0 | M9: =IF(C9<>"",(J9-L9),"") -> 2300 | N9: =IF(B9<>"",(IF(L9>G9,(L9-G9),0)),"") -> 0 | O9: =IF(B9<>"",(IF(P9="Bad debt",M9,0)),"") -> 0 | P9: =IF(B9<>"",(IF((_xlfn.XLOOKUP(C9,'Loan Out'!A:A,'Loan Out'!L:L))="Bad debt","Bad debt",IF(M9>0,"Pending","Settled"))),"") -> Pending
A10: =IF(C10<>"","Entry"&ROW()-1,"") -> Entry9 | B10: LN9 | Aluchio Caren | 1500 | 0 | 1500 | 45975 | C10: =IF(B10<>"",(LEFT(B10,FIND(" |",B10)-1)),"") -> LN9 | D10: =IF(C10="","",(_xlfn.XLOOKUP(C10,'Loan Out'!A:A,'Loan Out'!J:J))) -> 45975 | E10: =IF(C10="","",(_xlfn.XLOOKUP(C10,'Loan Out'!A:A,'Loan Out'!D:D))) -> 1500 | F10: =IF(C10="","",(_xlfn.XLOOKUP(C10,'Loan Out'!A:A,'Loan Out'!E:E))) -> 29 | G10: =IF(C10="","",(_xlfn.XLOOKUP(C10,'Loan Out'!A:A,'Loan Out'!F:F))) -> 1529 | H10: =IF(C10="","",(_xlfn.XLOOKUP(C10,'Loan Out'!A:A,'Loan Out'!G:G))) -> 0 | I10: =IF(C10="","",(_xlfn.XLOOKUP(C10,'Loan Out'!A:A,'Loan Out'!H:H))) -> 0 | J10: =IF(C10="","",(_xlfn.XLOOKUP(C10,'Loan Out'!A:A,'Loan Out'!I:I))) -> 1500 | K10: =IF(C10="","",(_xlfn.XLOOKUP(C10,'Loan Out'!A:A,'Loan Out'!J:J))) -> 45975 | L10: =IF(C10<>"",(SUMIF(Payments!C:C,C10,Payments!G:G)),"") -> 1600 | M10: =IF(C10<>"",(J10-L10),"") -> -100 | N10: =IF(B10<>"",(IF(L10>G10,(L10-G10),0)),"") -> 71 | O10: =IF(B10<>"",(IF(P10="Bad debt",M10,0)),"") -> 0 | P10: =IF(B10<>"",(IF((_xlfn.XLOOKUP(C10,'Loan Out'!A:A,'Loan Out'!L:L))="Bad debt","Bad debt",IF(M10>0,"Pending","Settled"))),"") -> Settled
A11: =IF(C11<>"","Entry"&ROW()-1,"") -> Entry10 | B11: LN10 | James Nganga | 1000 | 150 | 1150 | 45981 | C11: =IF(B11<>"",(LEFT(B11,FIND(" |",B11)-1)),"") -> LN10 | D11: =IF(C11="","",(_xlfn.XLOOKUP(C11,'Loan Out'!A:A,'Loan Out'!J:J))) -> 45981 | E11: =IF(C11="","",(_xlfn.XLOOKUP(C11,'Loan Out'!A:A,'Loan Out'!D:D))) -> 1000 | F11: =IF(C11="","",(_xlfn.XLOOKUP(C11,'Loan Out'!A:A,'Loan Out'!E:E))) -> 18 | G11: =IF(C11="","",(_xlfn.XLOOKUP(C11,'Loan Out'!A:A,'Loan Out'!F:F))) -> 1018 | H11: =IF(C11="","",(_xlfn.XLOOKUP(C11,'Loan Out'!A:A,'Loan Out'!G:G))) -> 0.15 | I11: =IF(C11="","",(_xlfn.XLOOKUP(C11,'Loan Out'!A:A,'Loan Out'!H:H))) -> 150 | J11: =IF(C11="","",(_xlfn.XLOOKUP(C11,'Loan Out'!A:A,'Loan Out'!I:I))) -> 1150 | K11: =IF(C11="","",(_xlfn.XLOOKUP(C11,'Loan Out'!A:A,'Loan Out'!J:J))) -> 45981 | L11: =IF(C11<>"",(SUMIF(Payments!C:C,C11,Payments!G:G)),"") -> 1150 | M11: =IF(C11<>"",(J11-L11),"") -> 0 | N11: =IF(B11<>"",(IF(L11>G11,(L11-G11),0)),"") -> 132 | O11: =IF(B11<>"",(IF(P11="Bad debt",M11,0)),"") -> 0 | P11: =IF(B11<>"",(IF((_xlfn.XLOOKUP(C11,'Loan Out'!A:A,'Loan Out'!L:L))="Bad debt","Bad debt",IF(M11>0,"Pending","Settled"))),"") -> Settled
A12: =IF(C12<>"","Entry"&ROW()-1,"") -> Entry11 | B12: LN11 | Elvis Mbaya | 15000 | 1500 | 16500 | 45983 | C12: =IF(B12<>"",(LEFT(B12,FIND(" |",B12)-1)),"") -> LN11 | D12: =IF(C12="","",(_xlfn.XLOOKUP(C12,'Loan Out'!A:A,'Loan Out'!J:J))) -> 45983 | E12: =IF(C12="","",(_xlfn.XLOOKUP(C12,'Loan Out'!A:A,'Loan Out'!D:D))) -> 15000 | F12: =IF(C12="","",(_xlfn.XLOOKUP(C12,'Loan Out'!A:A,'Loan Out'!E:E))) -> 60 | G12: =IF(C12="","",(_xlfn.XLOOKUP(C12,'Loan Out'!A:A,'Loan Out'!F:F))) -> 15060 | H12: =IF(C12="","",(_xlfn.XLOOKUP(C12,'Loan Out'!A:A,'Loan Out'!G:G))) -> 0.1 | I12: =IF(C12="","",(_xlfn.XLOOKUP(C12,'Loan Out'!A:A,'Loan Out'!H:H))) -> 1500 | J12: =IF(C12="","",(_xlfn.XLOOKUP(C12,'Loan Out'!A:A,'Loan Out'!I:I))) -> 16500 | K12: =IF(C12="","",(_xlfn.XLOOKUP(C12,'Loan Out'!A:A,'Loan Out'!J:J))) -> 45983 | L12: =IF(C12<>"",(SUMIF(Payments!C:C,C12,Payments!G:G)),"") -> 10000 | M12: =IF(C12<>"",(J12-L12),"") -> 6500 | N12: =IF(B12<>"",(IF(L12>G12,(L12-G12),0)),"") -> 0 | O12: =IF(B12<>"",(IF(P12="Bad debt",M12,0)),"") -> 0 | P12: =IF(B12<>"",(IF((_xlfn.XLOOKUP(C12,'Loan Out'!A:A,'Loan Out'!L:L))="Bad debt","Bad debt",IF(M12>0,"Pending","Settled"))),"") -> Pending
A13: =IF(C13<>"","Entry"&ROW()-1,"") -> Entry12 | B13: LN12 | Edmond Odongo | 5000 | 750 | 5750 | 45992 | C13: =IF(B13<>"",(LEFT(B13,FIND(" |",B13)-1)),"") -> LN12 | D13: =IF(C13="","",(_xlfn.XLOOKUP(C13,'Loan Out'!A:A,'Loan Out'!J:J))) -> 45992 | E13: =IF(C13="","",(_xlfn.XLOOKUP(C13,'Loan Out'!A:A,'Loan Out'!D:D))) -> 5000 | F13: =IF(C13="","",(_xlfn.XLOOKUP(C13,'Loan Out'!A:A,'Loan Out'!E:E))) -> 57 | G13: =IF(C13="","",(_xlfn.XLOOKUP(C13,'Loan Out'!A:A,'Loan Out'!F:F))) -> 5057 | H13: =IF(C13="","",(_xlfn.XLOOKUP(C13,'Loan Out'!A:A,'Loan Out'!G:G))) -> 0.15 | I13: =IF(C13="","",(_xlfn.XLOOKUP(C13,'Loan Out'!A:A,'Loan Out'!H:H))) -> 750 | J13: =IF(C13="","",(_xlfn.XLOOKUP(C13,'Loan Out'!A:A,'Loan Out'!I:I))) -> 5750 | K13: =IF(C13="","",(_xlfn.XLOOKUP(C13,'Loan Out'!A:A,'Loan Out'!J:J))) -> 45992 | L13: =IF(C13<>"",(SUMIF(Payments!C:C,C13,Payments!G:G)),"") -> 5750 | M13: =IF(C13<>"",(J13-L13),"") -> 0 | N13: =IF(B13<>"",(IF(L13>G13,(L13-G13),0)),"") -> 693 | O13: =IF(B13<>"",(IF(P13="Bad debt",M13,0)),"") -> 0 | P13: =IF(B13<>"",(IF((_xlfn.XLOOKUP(C13,'Loan Out'!A:A,'Loan Out'!L:L))="Bad debt","Bad debt",IF(M13>0,"Pending","Settled"))),"") -> Settled
... A20: =IF(C20<>"","Entry"&ROW()-1,"") -> Entry19 | B20: LN19 | Edmond Odongo | 1000 | 150 | 1150 | 46039 | C20: =IF(B20<>"",(LEFT(B20,FIND(" |",B20)-1)),"") -> LN19 | D20: =IF(C20="","",(_xlfn.XLOOKUP(C20,'Loan Out'!A:A,'Loan Out'!J:J))) -> 46039 | E20: =IF(C20="","",(_xlfn.XLOOKUP(C20,'Loan Out'!A:A,'Loan Out'!D:D))) -> 1000 | F20: =IF(C20="","",(_xlfn.XLOOKUP(C20,'Loan Out'!A:A,'Loan Out'!E:E))) -> 18 | G20: =IF(C20="","",(_xlfn.XLOOKUP(C20,'Loan Out'!A:A,'Loan Out'!F:F))) -> 1018 | H20: =IF(C20="","",(_xlfn.XLOOKUP(C20,'Loan Out'!A:A,'Loan Out'!G:G))) -> 0.15 | I20: =IF(C20="","",(_xlfn.XLOOKUP(C20,'Loan Out'!A:A,'Loan Out'!H:H))) -> 150 | J20: =IF(C20="","",(_xlfn.XLOOKUP(C20,'Loan Out'!A:A,'Loan Out'!I:I))) -> 1150 | K20: =IF(C20="","",(_xlfn.XLOOKUP(C20,'Loan Out'!A:A,'Loan Out'!J:J))) -> 46039 | L20: =IF(C20<>"",(SUMIF(Payments!C:C,C20,Payments!G:G)),"") -> 0 | M20: =IF(C20<>"",(J20-L20),"") -> 1150 | N20: =IF(B20<>"",(IF(L20>G20,(L20-G20),0)),"") -> 0 | O20: =IF(B20<>"",(IF(P20="Bad debt",M20,0)),"") -> 0 | P20: =IF(B20<>"",(IF((_xlfn.XLOOKUP(C20,'Loan Out'!A:A,'Loan Out'!L:L))="Bad debt","Bad debt",IF(M20>0,"Pending","Settled"))),"") -> Pending
A21: =IF(C21<>"","Entry"&ROW()-1,"") | C21: =IF(B21<>"",(LEFT(B21,FIND(" |",B21)-1)),"") | D21: =IF(C21="","",(_xlfn.XLOOKUP(C21,'Loan Out'!A:A,'Loan Out'!J:J))) | E21: =IF(C21="","",(_xlfn.XLOOKUP(C21,'Loan Out'!A:A,'Loan Out'!D:D))) | F21: =IF(C21="","",(_xlfn.XLOOKUP(C21,'Loan Out'!A:A,'Loan Out'!E:E))) | G21: =IF(C21="","",(_xlfn.XLOOKUP(C21,'Loan Out'!A:A,'Loan Out'!F:F))) | H21: =IF(C21="","",(_xlfn.XLOOKUP(C21,'Loan Out'!A:A,'Loan Out'!G:G))) | I21: =IF(C21="","",(_xlfn.XLOOKUP(C21,'Loan Out'!A:A,'Loan Out'!H:H))) | J21: =IF(C21="","",(_xlfn.XLOOKUP(C21,'Loan Out'!A:A,'Loan Out'!I:I))) | K21: =IF(C21="","",(_xlfn.XLOOKUP(C21,'Loan Out'!A:A,'Loan Out'!J:J))) | L21: =IF(C21<>"",(SUMIF(Payments!C:C,C21,Payments!G:G)),"") | M21: =IF(C21<>"",(J21-L21),"") | N21: =IF(B21<>"",(IF(L21>G21,(L21-G21),0)),"") | O21: =IF(B21<>"",(IF(P21="Bad debt",M21,0)),"") | P21: =IF(B21<>"",(IF((_xlfn.XLOOKUP(C21,'Loan Out'!A:A,'Loan Out'!L:L))="Bad debt","Bad debt",IF(M21>0,"Pending","Settled"))),"")
A22: =IF(C22<>"","Entry"&ROW()-1,"") | C22: =IF(B22<>"",(LEFT(B22,FIND(" |",B22)-1)),"") | D22: =IF(C22="","",(_xlfn.XLOOKUP(C22,'Loan Out'!A:A,'Loan Out'!J:J))) | E22: =IF(C22="","",(_xlfn.XLOOKUP(C22,'Loan Out'!A:A,'Loan Out'!D:D))) | F22: =IF(C22="","",(_xlfn.XLOOKUP(C22,'Loan Out'!A:A,'Loan Out'!E:E))) | G22: =IF(C22="","",(_xlfn.XLOOKUP(C22,'Loan Out'!A:A,'Loan Out'!F:F))) | H22: =IF(C22="","",(_xlfn.XLOOKUP(C22,'Loan Out'!A:A,'Loan Out'!G:G))) | I22: =IF(C22="","",(_xlfn.XLOOKUP(C22,'Loan Out'!A:A,'Loan Out'!H:H))) | J22: =IF(C22="","",(_xlfn.XLOOKUP(C22,'Loan Out'!A:A,'Loan Out'!I:I))) | K22: =IF(C22="","",(_xlfn.XLOOKUP(C22,'Loan Out'!A:A,'Loan Out'!J:J))) | L22: =IF(C22<>"",(SUMIF(Payments!C:C,C22,Payments!G:G)),"") | M22: =IF(C22<>"",(J22-L22),"") | N22: =IF(B22<>"",(IF(L22>G22,(L22-G22),0)),"") | O22: =IF(B22<>"",(IF(P22="Bad debt",M22,0)),"") | P22: =IF(B22<>"",(IF((_xlfn.XLOOKUP(C22,'Loan Out'!A:A,'Loan Out'!L:L))="Bad debt","Bad debt",IF(M22>0,"Pending","Settled"))),"")
A23: =IF(C23<>"","Entry"&ROW()-1,"") | C23: =IF(B23<>"",(LEFT(B23,FIND(" |",B23)-1)),"") | D23: =IF(C23="","",(_xlfn.XLOOKUP(C23,'Loan Out'!A:A,'Loan Out'!J:J))) | E23: =IF(C23="","",(_xlfn.XLOOKUP(C23,'Loan Out'!A:A,'Loan Out'!D:D))) | F23: =IF(C23="","",(_xlfn.XLOOKUP(C23,'Loan Out'!A:A,'Loan Out'!E:E))) | G23: =IF(C23="","",(_xlfn.XLOOKUP(C23,'Loan Out'!A:A,'Loan Out'!F:F))) | H23: =IF(C23="","",(_xlfn.XLOOKUP(C23,'Loan Out'!A:A,'Loan Out'!G:G))) | I23: =IF(C23="","",(_xlfn.XLOOKUP(C23,'Loan Out'!A:A,'Loan Out'!H:H))) | J23: =IF(C23="","",(_xlfn.XLOOKUP(C23,'Loan Out'!A:A,'Loan Out'!I:I))) | K23: =IF(C23="","",(_xlfn.XLOOKUP(C23,'Loan Out'!A:A,'Loan Out'!J:J))) | L23: =IF(C23<>"",(SUMIF(Payments!C:C,C23,Payments!G:G)),"") | M23: =IF(C23<>"",(J23-L23),"") | N23: =IF(B23<>"",(IF(L23>G23,(L23-G23),0)),"") | O23: =IF(B23<>"",(IF(P23="Bad debt",M23,0)),"") | P23: =IF(B23<>"",(IF((_xlfn.XLOOKUP(C23,'Loan Out'!A:A,'Loan Out'!L:L))="Bad debt","Bad debt",IF(M23>0,"Pending","Settled"))),"")
A24: =IF(C24<>"","Entry"&ROW()-1,"") | C24: =IF(B24<>"",(LEFT(B24,FIND(" |",B24)-1)),"") | D24: =IF(C24="","",(_xlfn.XLOOKUP(C24,'Loan Out'!A:A,'Loan Out'!J:J))) | E24: =IF(C24="","",(_xlfn.XLOOKUP(C24,'Loan Out'!A:A,'Loan Out'!D:D))) | F24: =IF(C24="","",(_xlfn.XLOOKUP(C24,'Loan Out'!A:A,'Loan Out'!E:E))) | G24: =IF(C24="","",(_xlfn.XLOOKUP(C24,'Loan Out'!A:A,'Loan Out'!F:F))) | H24: =IF(C24="","",(_xlfn.XLOOKUP(C24,'Loan Out'!A:A,'Loan Out'!G:G))) | I24: =IF(C24="","",(_xlfn.XLOOKUP(C24,'Loan Out'!A:A,'Loan Out'!H:H))) | J24: =IF(C24="","",(_xlfn.XLOOKUP(C24,'Loan Out'!A:A,'Loan Out'!I:I))) | K24: =IF(C24="","",(_xlfn.XLOOKUP(C24,'Loan Out'!A:A,'Loan Out'!J:J))) | L24: =IF(C24<>"",(SUMIF(Payments!C:C,C24,Payments!G:G)),"") | M24: =IF(C24<>"",(J24-L24),"") | N24: =IF(B24<>"",(IF(L24>G24,(L24-G24),0)),"") | O24: =IF(B24<>"",(IF(P24="Bad debt",M24,0)),"") | P24: =IF(B24<>"",(IF((_xlfn.XLOOKUP(C24,'Loan Out'!A:A,'Loan Out'!L:L))="Bad debt","Bad debt",IF(M24>0,"Pending","Settled"))),"")
A25: =IF(C25<>"","Entry"&ROW()-1,"") | C25: =IF(B25<>"",(LEFT(B25,FIND(" |",B25)-1)),"") | D25: =IF(C25="","",(_xlfn.XLOOKUP(C25,'Loan Out'!A:A,'Loan Out'!J:J))) | E25: =IF(C25="","",(_xlfn.XLOOKUP(C25,'Loan Out'!A:A,'Loan Out'!D:D))) | F25: =IF(C25="","",(_xlfn.XLOOKUP(C25,'Loan Out'!A:A,'Loan Out'!E:E))) | G25: =IF(C25="","",(_xlfn.XLOOKUP(C25,'Loan Out'!A:A,'Loan Out'!F:F))) | H25: =IF(C25="","",(_xlfn.XLOOKUP(C25,'Loan Out'!A:A,'Loan Out'!G:G))) | I25: =IF(C25="","",(_xlfn.XLOOKUP(C25,'Loan Out'!A:A,'Loan Out'!H:H))) | J25: =IF(C25="","",(_xlfn.XLOOKUP(C25,'Loan Out'!A:A,'Loan Out'!I:I))) | K25: =IF(C25="","",(_xlfn.XLOOKUP(C25,'Loan Out'!A:A,'Loan Out'!J:J))) | L25: =IF(C25<>"",(SUMIF(Payments!C:C,C25,Payments!G:G)),"") | M25: =IF(C25<>"",(J25-L25),"") | N25: =IF(B25<>"",(IF(L25>G25,(L25-G25),0)),"") | O25: =IF(B25<>"",(IF(P25="Bad debt",M25,0)),"") | P25: =IF(B25<>"",(IF((_xlfn.XLOOKUP(C25,'Loan Out'!A:A,'Loan Out'!L:L))="Bad debt","Bad debt",IF(M25>0,"Pending","Settled"))),"")
A26: =IF(C26<>"","Entry"&ROW()-1,"") | C26: =IF(B26<>"",(LEFT(B26,FIND(" |",B26)-1)),"") | D26: =IF(C26="","",(_xlfn.XLOOKUP(C26,'Loan Out'!A:A,'Loan Out'!J:J))) | E26: =IF(C26="","",(_xlfn.XLOOKUP(C26,'Loan Out'!A:A,'Loan Out'!D:D))) | F26: =IF(C26="","",(_xlfn.XLOOKUP(C26,'Loan Out'!A:A,'Loan Out'!E:E))) | G26: =IF(C26="","",(_xlfn.XLOOKUP(C26,'Loan Out'!A:A,'Loan Out'!F:F))) | H26: =IF(C26="","",(_xlfn.XLOOKUP(C26,'Loan Out'!A:A,'Loan Out'!G:G))) | I26: =IF(C26="","",(_xlfn.XLOOKUP(C26,'Loan Out'!A:A,'Loan Out'!H:H))) | J26: =IF(C26="","",(_xlfn.XLOOKUP(C26,'Loan Out'!A:A,'Loan Out'!I:I))) | K26: =IF(C26="","",(_xlfn.XLOOKUP(C26,'Loan Out'!A:A,'Loan Out'!J:J))) | L26: =IF(C26<>"",(SUMIF(Payments!C:C,C26,Payments!G:G)),"") | M26: =IF(C26<>"",(J26-L26),"") | N26: =IF(B26<>"",(IF(L26>G26,(L26-G26),0)),"") | O26: =IF(B26<>"",(IF(P26="Bad debt",M26,0)),"") | P26: =IF(B26<>"",(IF((_xlfn.XLOOKUP(C26,'Loan Out'!A:A,'Loan Out'!L:L))="Bad debt","Bad debt",IF(M26>0,"Pending","Settled"))),"")
A27: =IF(C27<>"","Entry"&ROW()-1,"") | C27: =IF(B27<>"",(LEFT(B27,FIND(" |",B27)-1)),"") | D27: =IF(C27="","",(_xlfn.XLOOKUP(C27,'Loan Out'!A:A,'Loan Out'!J:J))) | E27: =IF(C27="","",(_xlfn.XLOOKUP(C27,'Loan Out'!A:A,'Loan Out'!D:D))) | F27: =IF(C27="","",(_xlfn.XLOOKUP(C27,'Loan Out'!A:A,'Loan Out'!E:E))) | G27: =IF(C27="","",(_xlfn.XLOOKUP(C27,'Loan Out'!A:A,'Loan Out'!F:F))) | H27: =IF(C27="","",(_xlfn.XLOOKUP(C27,'Loan Out'!A:A,'Loan Out'!G:G))) | I27: =IF(C27="","",(_xlfn.XLOOKUP(C27,'Loan Out'!A:A,'Loan Out'!H:H))) | J27: =IF(C27="","",(_xlfn.XLOOKUP(C27,'Loan Out'!A:A,'Loan Out'!I:I))) | K27: =IF(C27="","",(_xlfn.XLOOKUP(C27,'Loan Out'!A:A,'Loan Out'!J:J))) | L27: =IF(C27<>"",(SUMIF(Payments!C:C,C27,Payments!G:G)),"") | M27: =IF(C27<>"",(J27-L27),"") | N27: =IF(B27<>"",(IF(L27>G27,(L27-G27),0)),"") | O27: =IF(B27<>"",(IF(P27="Bad debt",M27,0)),"") | P27: =IF(B27<>"",(IF((_xlfn.XLOOKUP(C27,'Loan Out'!A:A,'Loan Out'!L:L))="Bad debt","Bad debt",IF(M27>0,"Pending","Settled"))),"")
A28: =IF(C28<>"","Entry"&ROW()-1,"") | C28: =IF(B28<>"",(LEFT(B28,FIND(" |",B28)-1)),"") | D28: =IF(C28="","",(_xlfn.XLOOKUP(C28,'Loan Out'!A:A,'Loan Out'!J:J))) | E28: =IF(C28="","",(_xlfn.XLOOKUP(C28,'Loan Out'!A:A,'Loan Out'!D:D))) | F28: =IF(C28="","",(_xlfn.XLOOKUP(C28,'Loan Out'!A:A,'Loan Out'!E:E))) | G28: =IF(C28="","",(_xlfn.XLOOKUP(C28,'Loan Out'!A:A,'Loan Out'!F:F))) | H28: =IF(C28="","",(_xlfn.XLOOKUP(C28,'Loan Out'!A:A,'Loan Out'!G:G))) | I28: =IF(C28="","",(_xlfn.XLOOKUP(C28,'Loan Out'!A:A,'Loan Out'!H:H))) | J28: =IF(C28="","",(_xlfn.XLOOKUP(C28,'Loan Out'!A:A,'Loan Out'!I:I))) | K28: =IF(C28="","",(_xlfn.XLOOKUP(C28,'Loan Out'!A:A,'Loan Out'!J:J))) | L28: =IF(C28<>"",(SUMIF(Payments!C:C,C28,Payments!G:G)),"") | M28: =IF(C28<>"",(J28-L28),"") | N28: =IF(B28<>"",(IF(L28>G28,(L28-G28),0)),"") | O28: =IF(B28<>"",(IF(P28="Bad debt",M28,0)),"") | P28: =IF(B28<>"",(IF((_xlfn.XLOOKUP(C28,'Loan Out'!A:A,'Loan Out'!L:L))="Bad debt","Bad debt",IF(M28>0,"Pending","Settled"))),"")
A29: =IF(C29<>"","Entry"&ROW()-1,"") | C29: =IF(B29<>"",(LEFT(B29,FIND(" |",B29)-1)),"") | D29: =IF(C29="","",(_xlfn.XLOOKUP(C29,'Loan Out'!A:A,'Loan Out'!J:J))) | E29: =IF(C29="","",(_xlfn.XLOOKUP(C29,'Loan Out'!A:A,'Loan Out'!D:D))) | F29: =IF(C29="","",(_xlfn.XLOOKUP(C29,'Loan Out'!A:A,'Loan Out'!E:E))) | G29: =IF(C29="","",(_xlfn.XLOOKUP(C29,'Loan Out'!A:A,'Loan Out'!F:F))) | H29: =IF(C29="","",(_xlfn.XLOOKUP(C29,'Loan Out'!A:A,'Loan Out'!G:G))) | I29: =IF(C29="","",(_xlfn.XLOOKUP(C29,'Loan Out'!A:A,'Loan Out'!H:H))) | J29: =IF(C29="","",(_xlfn.XLOOKUP(C29,'Loan Out'!A:A,'Loan Out'!I:I))) | K29: =IF(C29="","",(_xlfn.XLOOKUP(C29,'Loan Out'!A:A,'Loan Out'!J:J))) | L29: =IF(C29<>"",(SUMIF(Payments!C:C,C29,Payments!G:G)),"") | M29: =IF(C29<>"",(J29-L29),"") | N29: =IF(B29<>"",(IF(L29>G29,(L29-G29),0)),"") | O29: =IF(B29<>"",(IF(P29="Bad debt",M29,0)),"") | P29: =IF(B29<>"",(IF((_xlfn.XLOOKUP(C29,'Loan Out'!A:A,'Loan Out'!L:L))="Bad debt","Bad debt",IF(M29>0,"Pending","Settled"))),"")
A30: =IF(C30<>"","Entry"&ROW()-1,"") | C30: =IF(B30<>"",(LEFT(B30,FIND(" |",B30)-1)),"") | D30: =IF(C30="","",(_xlfn.XLOOKUP(C30,'Loan Out'!A:A,'Loan Out'!J:J))) | E30: =IF(C30="","",(_xlfn.XLOOKUP(C30,'Loan Out'!A:A,'Loan Out'!D:D))) | F30: =IF(C30="","",(_xlfn.XLOOKUP(C30,'Loan Out'!A:A,'Loan Out'!E:E))) | G30: =IF(C30="","",(_xlfn.XLOOKUP(C30,'Loan Out'!A:A,'Loan Out'!F:F))) | H30: =IF(C30="","",(_xlfn.XLOOKUP(C30,'Loan Out'!A:A,'Loan Out'!G:G))) | I30: =IF(C30="","",(_xlfn.XLOOKUP(C30,'Loan Out'!A:A,'Loan Out'!H:H))) | J30: =IF(C30="","",(_xlfn.XLOOKUP(C30,'Loan Out'!A:A,'Loan Out'!I:I))) | K30: =IF(C30="","",(_xlfn.XLOOKUP(C30,'Loan Out'!A:A,'Loan Out'!J:J))) | L30: =IF(C30<>"",(SUMIF(Payments!C:C,C30,Payments!G:G)),"") | M30: =IF(C30<>"",(J30-L30),"") | N30: =IF(B30<>"",(IF(L30>G30,(L30-G30),0)),"") | O30: =IF(B30<>"",(IF(P30="Bad debt",M30,0)),"") | P30: =IF(B30<>"",(IF((_xlfn.XLOOKUP(C30,'Loan Out'!A:A,'Loan Out'!L:L))="Bad debt","Bad debt",IF(M30>0,"Pending","Settled"))),"")
A31: =IF(C31<>"","Entry"&ROW()-1,"") | C31: =IF(B31<>"",(LEFT(B31,FIND(" |",B31)-1)),"") | D31: =IF(C31="","",(_xlfn.XLOOKUP(C31,'Loan Out'!A:A,'Loan Out'!J:J))) | E31: =IF(C31="","",(_xlfn.XLOOKUP(C31,'Loan Out'!A:A,'Loan Out'!D:D))) | F31: =IF(C31="","",(_xlfn.XLOOKUP(C31,'Loan Out'!A:A,'Loan Out'!E:E))) | G31: =IF(C31="","",(_xlfn.XLOOKUP(C31,'Loan Out'!A:A,'Loan Out'!F:F))) | H31: =IF(C31="","",(_xlfn.XLOOKUP(C31,'Loan Out'!A:A,'Loan Out'!G:G))) | I31: =IF(C31="","",(_xlfn.XLOOKUP(C31,'Loan Out'!A:A,'Loan Out'!H:H))) | J31: =IF(C31="","",(_xlfn.XLOOKUP(C31,'Loan Out'!A:A,'Loan Out'!I:I))) | K31: =IF(C31="","",(_xlfn.XLOOKUP(C31,'Loan Out'!A:A,'Loan Out'!J:J))) | L31: =IF(C31<>"",(SUMIF(Payments!C:C,C31,Payments!G:G)),"") | M31: =IF(C31<>"",(J31-L31),"") | N31: =IF(B31<>"",(IF(L31>G31,(L31-G31),0)),"") | O31: =IF(B31<>"",(IF(P31="Bad debt",M31,0)),"") | P31: =IF(B31<>"",(IF((_xlfn.XLOOKUP(C31,'Loan Out'!A:A,'Loan Out'!L:L))="Bad debt","Bad debt",IF(M31>0,"Pending","Settled"))),"")
A32: =IF(C32<>"","Entry"&ROW()-1,"") | C32: =IF(B32<>"",(LEFT(B32,FIND(" |",B32)-1)),"") | D32: =IF(C32="","",(_xlfn.XLOOKUP(C32,'Loan Out'!A:A,'Loan Out'!J:J))) | E32: =IF(C32="","",(_xlfn.XLOOKUP(C32,'Loan Out'!A:A,'Loan Out'!D:D))) | F32: =IF(C32="","",(_xlfn.XLOOKUP(C32,'Loan Out'!A:A,'Loan Out'!E:E))) | G32: =IF(C32="","",(_xlfn.XLOOKUP(C32,'Loan Out'!A:A,'Loan Out'!F:F))) | H32: =IF(C32="","",(_xlfn.XLOOKUP(C32,'Loan Out'!A:A,'Loan Out'!G:G))) | I32: =IF(C32="","",(_xlfn.XLOOKUP(C32,'Loan Out'!A:A,'Loan Out'!H:H))) | J32: =IF(C32="","",(_xlfn.XLOOKUP(C32,'Loan Out'!A:A,'Loan Out'!I:I))) | K32: =IF(C32="","",(_xlfn.XLOOKUP(C32,'Loan Out'!A:A,'Loan Out'!J:J))) | L32: =IF(C32<>"",(SUMIF(Payments!C:C,C32,Payments!G:G)),"") | M32: =IF(C32<>"",(J32-L32),"") | N32: =IF(B32<>"",(IF(L32>G32,(L32-G32),0)),"") | O32: =IF(B32<>"",(IF(P32="Bad debt",M32,0)),"") | P32: =IF(B32<>"",(IF((_xlfn.XLOOKUP(C32,'Loan Out'!A:A,'Loan Out'!L:L))="Bad debt","Bad debt",IF(M32>0,"Pending","Settled"))),"")
... A250: =IF(C250<>"","Entry"&ROW()-1,"") | C250: =IF(B250<>"",(LEFT(B250,FIND(" |",B250)-1)),"") | D250: =IF(C250="","",(_xlfn.XLOOKUP(C250,'Loan Out'!A:A,'Loan Out'!J:J))) | E250: =IF(C250="","",(_xlfn.XLOOKUP(C250,'Loan Out'!A:A,'Loan Out'!D:D))) | F250: =IF(C250="","",(_xlfn.XLOOKUP(C250,'Loan Out'!A:A,'Loan Out'!E:E))) | G250: =IF(C250="","",(_xlfn.XLOOKUP(C250,'Loan Out'!A:A,'Loan Out'!F:F))) | H250: =IF(C250="","",(_xlfn.XLOOKUP(C250,'Loan Out'!A:A,'Loan Out'!G:G))) | I250: =IF(C250="","",(_xlfn.XLOOKUP(C250,'Loan Out'!A:A,'Loan Out'!H:H))) | J250: =IF(C250="","",(_xlfn.XLOOKUP(C250,'Loan Out'!A:A,'Loan Out'!I:I))) | K250: =IF(C250="","",(_xlfn.XLOOKUP(C250,'Loan Out'!A:A,'Loan Out'!J:J))) | L250: =IF(C250<>"",(SUMIF(Payments!C:C,C250,Payments!G:G)),"") | M250: =IF(C250<>"",(J250-L250),"") | N250: =IF(B250<>"",(IF(L250>G250,(L250-G250),0)),"") | O250: =IF(B250<>"",(IF(P250="Bad debt",M250,0)),"") | P250: =IF(B250<>"",(IF((_xlfn.XLOOKUP(C250,'Loan Out'!A:A,'Loan Out'!L:L))="Bad debt","Bad debt",IF(M250>0,"Pending","Settled"))),"")

Sheet Pivot1-Sums
A3: Sum of Unpaid Amount | B3: Sum of Remittance Amount
A4: 46600 | B4: 37600

Sheet Pivot2-Status count
A3: Loan Status | B3: Count of Loan Status
B4: 230
A5: Bad debt | B5: 2
A6: Pending | B6: 10
A7: Settled | B7: 7
A8: Grand Total | B8: 249
